aio_logstash/__init__.py
aio_logstash/constants.py
aio_logstash/formatter.py
aio_logstash/handler.py
aio_logstash-0.1.0.dist-info/LICENSE
aio_logstash-0.1.0.dist-info/WHEEL
aio_logstash-0.1.0.dist-info/METADATA
aio_logstash-0.1.0.dist-info/RECORD
