Metadata-Version: 2.1
Name: aio-logstash
Version: 0.1.0
Summary: Python AsyncIO Logstash Logger
Home-page: https://github.com/SinaKhorami/aio-logstash
License: UNKNOWN
Keywords: asyncio logstash logger
Author: Sina Khorami
Author-email: sinakhorami94@gmail.com
Requires-Python: >=3.7
Classifier: License :: OSI Approved :: MIT License
Classifier: Programming Language :: Python :: 3
Classifier: Programming Language :: Python :: 3.7
